{
    "本地相关": [
             {
             "id":1,
             "name": "消息通知",
             "type": "switch"
             },
             {
             "id":2,
             "name": "本地存储",
             "type": "info"
             },
             {
             "id":3,
             "name": "语言设置",
             "type": "info"
             }
             ],
    "设备相关": [
             {
             "id":4,
             "name": "自动下载拍照文件",
             "type": "switch"
             },
             {
             "id":5,
             "name": "同步最新5条视频",
             "type": "switch"
             },
             {
             "id":6,
             "name": "保存图片到手机相册",
             "type": "switch"
             }
             ]
}